Metadata-Version: 2.1
Name: nirdust
Version: 0.2.0
Summary: Measure temperature of hot dust in type 2 AGN
Home-page: https://github.com/Gaiana/nirdust
Author: ['Gaia Gaspar', 'Jose Alacoria']
Author-email: gaiagaspar@gmail.com
License: MIT
Keywords: nirdust,dust,AGN,NIR,temperatures
Platform: UNKNOWN
Classifier: Intended Audience :: Education
Classifier: Intended Audience :: Science/Research
Classifier: License :: OSI Approved :: MIT License
Classifier: Operating System :: OS Independent
Classifier: Programming Language :: Python
Classifier: Programming Language :: Python :: 3.8
License-File: LICENSE
